setup.py
distributionspack/Binomialdistribution.py
distributionspack/Gaussiandistribution.py
distributionspack/Generaldistribution.py
distributionspack/__init__.py
distributionspack.egg-info/PKG-INFO
distributionspack.egg-info/SOURCES.txt
distributionspack.egg-info/dependency_links.txt
distributionspack.egg-info/not-zip-safe
distributionspack.egg-info/top_level.txt