Metadata-Version: 1.0
Name: distributionspack
Version: 0.1
Summary: Gaussian distributions
Home-page: UNKNOWN
Author: vijaykrishnaa
Author-email: vk596466@gmail.com
License: UNKNOWN
Platform: UNKNOWN
